{
    "caption": "Energetic Hungarian folk rock with violin and acoustic guitar, male vocals, driving rhythm section, traditional Eastern European scales",
    "lyrics": "[verse]\nWalking through the fields of gold\nWhere my ancestors roamed of old\nThe Tisza river calls my name\nNothing here has stayed the same\n\n[chorus]\nRising like the morning sun\nFighting till the battle's won\nHungarian blood runs deep and true\nSkies of red and white and green and blue\n\n[verse]\nFire in the village square\nViolines ring through the air\nDancing feet on cobblestone\nEvery heart has found its home\n\n[chorus]\nRising like the morning sun\nFighting till the battle's won\nHungarian blood runs deep and true\nSkies of red and white and green and blue\n\n[bridge]\nFrom the mountains to the plain\nThrough the sun and through the rain\nWe will carry on this song\nTo remind us where we belong\n\n[chorus]\nRising like the morning sun\nFighting till the battle's won\nHungarian blood runs deep and true\nSkies of red and white and green and blue\n\n[outro]\nThe violin fades into the night\nBut the fire still burns bright",
    "inference_steps": 8,
    "shift": 3.0,
    "vocal_language": "en"
}
